falcon_jsonify/__init__.py
falcon_jsonify-1.2.dist-info/METADATA
falcon_jsonify-1.2.dist-info/RECORD
falcon_jsonify-1.2.dist-info/WHEEL
falcon_jsonify-1.2.dist-info/top_level.txt
