Metadata-Version: 2.1
Name: falcon-jsonify
Version: 1.2
Summary: Falcon middleware to serialize/deserialize JSON with built-in input validation
Home-page: https://github.com/AndreiRegiani/falcon-jsonify
Author: Andrei Regiani
Author-email: andrei.cpp@gmail.com
License: MIT
Keywords: falcon json jsonify validation validator middleware
Platform: UNKNOWN
Classifier: Development Status :: 5 - Production/Stable
Classifier: Intended Audience :: Developers
Classifier: Operating System :: OS Independent
Classifier: Programming Language :: Python
Classifier: Programming Language :: Python :: 2
Classifier: Programming Language :: Python :: 2.7
Classifier: Programming Language :: Python :: 3
Classifier: Programming Language :: Python :: 3.4
Classifier: Topic :: Software Development :: Libraries
Requires-Dist: falcon (>=0.3)
Requires-Dist: six
